odoo10_addon_shopinvader_custom_attribute-10.0.1.0.0.99.dev10-py3.8-nspkg.pth
odoo/addons/shopinvader_custom_attribute/README.rst
odoo/addons/shopinvader_custom_attribute/__init__.py
odoo/addons/shopinvader_custom_attribute/__manifest__.py
odoo/addons/shopinvader_custom_attribute/data/ir_export_product.xml
odoo/addons/shopinvader_custom_attribute/demo/product_filter.xml
odoo/addons/shopinvader_custom_attribute/i18n/shopinvader_custom_attribute.pot
odoo/addons/shopinvader_custom_attribute/models/__init__.py
odoo/addons/shopinvader_custom_attribute/models/product_filter.py
odoo/addons/shopinvader_custom_attribute/models/shopinvader_variant.py
odoo/addons/shopinvader_custom_attribute/readme/CONTRIBUTORS.rst
odoo/addons/shopinvader_custom_attribute/readme/DESCRIPTION.rst
odoo/addons/shopinvader_custom_attribute/static/description/index.html
odoo/addons/shopinvader_custom_attribute/tests/__init__.py
odoo/addons/shopinvader_custom_attribute/tests/test_product.py
odoo/addons/shopinvader_custom_attribute/views/product_filter_view.xml
odoo10_addon_shopinvader_custom_attribute-10.0.1.0.0.99.dev10.dist-info/METADATA
odoo10_addon_shopinvader_custom_attribute-10.0.1.0.0.99.dev10.dist-info/WHEEL
odoo10_addon_shopinvader_custom_attribute-10.0.1.0.0.99.dev10.dist-info/namespace_packages.txt
odoo10_addon_shopinvader_custom_attribute-10.0.1.0.0.99.dev10.dist-info/top_level.txt
odoo10_addon_shopinvader_custom_attribute-10.0.1.0.0.99.dev10.dist-info/RECORD
