Metadata-Version: 2.1
Name: odoo10-addon-shopinvader-custom-attribute
Version: 10.0.1.0.0.99.dev10
Summary: Integrate your custom attribute in your website
Home-page: https://github.com/shopinvader/odoo-shopinvader
Author: Akretion
License: AGPL-3
Platform: UNKNOWN
Classifier: Programming Language :: Python
Classifier: Framework :: Odoo
Classifier: License :: OSI Approved :: GNU Affero General Public License v3
Requires-Python: ~=2.7
Requires-Dist: odoo10-addon-product-custom-attribute
Requires-Dist: odoo10-addon-shopinvader
Requires-Dist: odoo (<10.1dev,>=10.0)
